openseries/__init__.py
openseries/_common_model.py
openseries/_risk.py
openseries/datefixer.py
openseries/frame.py
openseries/html_utils.py
openseries/load_plotly.py
openseries/owntypes.py
openseries/plotly_captor_logo.json
openseries/plotly_layouts.json
openseries/portfoliotools.py
openseries/py.typed
openseries/report.py
openseries/series.py
openseries/simulation.py
openseries-2.1.5.dist-info/METADATA
openseries-2.1.5.dist-info/WHEEL
openseries-2.1.5.dist-info/licenses/LICENSE.md
openseries-2.1.5.dist-info/RECORD
