Metadata-Version: 2.4
Name: openseries
Version: 2.1.5
Summary: Tools for analyzing financial timeseries.
License-Expression: BSD-3-Clause
License-File: LICENSE.md
Keywords: python,finance,fintech,data-science,timeseries,timeseries-data,timeseries-analysis,investment,investment-analysis,investing
Author: Martin Karrin
Author-email: martin.karrin@captor.se
Maintainer: Martin Karrin
Maintainer-email: martin.karrin@captor.se
Requires-Python: >=3.11,<3.15
Classifier: Programming Language :: Python :: 3.11
Classifier: Programming Language :: Python :: 3.12
Classifier: Programming Language :: Python :: 3.13
Classifier: Programming Language :: Python :: 3.14
Classifier: Intended Audience :: Financial and Insurance Industry
Classifier: Topic :: Office/Business :: Financial :: Investment
Classifier: Natural Language :: English
Classifier: Development Status :: 5 - Production/Stable
Classifier: Operating System :: OS Independent
Classifier: Framework :: Pydantic
Requires-Dist: exchange-calendars (>=4.8)
Requires-Dist: holidays (>=0.30)
Requires-Dist: numpy (>=1.23.2)
Requires-Dist: openpyxl (>=3.1.2)
Requires-Dist: pandas (>=2.1.2)
Requires-Dist: plotly (>=5.18.0)
Requires-Dist: pydantic (>=2.5.2)
Requires-Dist: python-dateutil (>=2.8.2)
Requires-Dist: requests (>=2.20.0)
Requires-Dist: scikit-learn (>=1.4.0)
Requires-Dist: scipy (>=1.14.1)
Project-URL: Documentation, https://openseries.readthedocs.io/
Project-URL: Homepage, https://captorab.github.io/openseries/
Project-URL: Issue Tracker, https://github.com/CaptorAB/openseries/issues
Project-URL: Release Notes, https://github.com/CaptorAB/openseries/releases
Project-URL: Source, https://github.com/CaptorAB/openseries
